apollo_python/__init__.py
apollo_python/__version__.py
apollo_python/apollo_client.py
apollo_python/core.py
apollo_python-1.1.5.dist-info/LICENSE
apollo_python-1.1.5.dist-info/METADATA
apollo_python-1.1.5.dist-info/WHEEL
apollo_python-1.1.5.dist-info/top_level.txt
apollo_python-1.1.5.dist-info/RECORD
