Metadata-Version: 2.1
Name: apollo-python
Version: 1.1.5
Summary: A simple python library for apollo config client.
Home-page: https://github.com/onecer/apollo-python
Author: Onecer
Author-email: yinyongyou@gmail.com
License: MIT
Classifier: License :: OSI Approved :: MIT License
Classifier: Programming Language :: Python
Classifier: Programming Language :: Python :: 3
Classifier: Programming Language :: Python :: 3.6
Classifier: Programming Language :: Python :: Implementation :: CPython
Classifier: Programming Language :: Python :: Implementation :: PyPy
Requires-Python: >=3.6.0
License-File: LICENSE
Requires-Dist: loguru
Requires-Dist: PyYAML
